LICENSE
MANIFEST.in
Makefile
README.md
ec2metadata
python3-ec2metadata.spec
setup.py
lib/ec2metadata/VERSION
lib/ec2metadata/__init__.py
lib/ec2metadata/ec2metautils.py
lib/ec2metadata.egg-info/PKG-INFO
lib/ec2metadata.egg-info/SOURCES.txt
lib/ec2metadata.egg-info/dependency_links.txt
lib/ec2metadata.egg-info/top_level.txt