Metadata-Version: 1.0
Name: ec2metadata
Version: 2.0.1
Summary: Command-line tool to collect EC2 instance meta data
Home-page: https://github.com/SUSE/Enceladus
Author: Alon Swartz, SUSE
Author-email: alon@turnkeylinux.org, public-cloud-dev@susecloud.net
License: GPLv3+
Platform: UNKNOWN
